{
  "med_conditons_array": [
    {
      "title": "ngs1",
      "conditions": [
        "Kidney cancer",
        "Leukemia",
        "Liver cancer",
        "Non-Hodgkins lymphoma",
        "Bladder cancer",
        "Acute Myeloid Leukemia (AML)",
        "Aplastic Anemia or myelodysplastic syndrome",
        "Brain cancer",
        "Blood cancer",
        "Chronic Kidney Disease",
        "Central nervous system cancer",
        "End Stage Renal Disease",
        "Esophageal Cancer",
        "Multiple Myeloma",
        "Parkinsons Disease",
        "Rectal Cancer",
        "Renal Toxicity",
        "Systemic Scleroderma / Systemic Sclerosis",
        "Male Breast Cancer",
        "Miscarriage / Fetal Death - Is the facility where the miscarriage was treated on Camp Lejeune or in Jacksonville, North Carolina? – if no, disqualify"
      ]
    },
    {
      "title": "ngs1 birth defect",
      "conditions": [
        "Anomalous pulmonary venous return",
        "Aortic valve stenosis",
        "Atrial septal defect",
        "Atrial septal defect + OL",
        "Cardiomyopathy",
        "Coarctation of the aorta",
        "Coarctation of the aorta + OL",
        "Dextrocardia with minor lesions",
        "Double outlet right ventricle",
        "Double aortic arch",
        "Endocardial cushion defect",
        "Hypoplastic left heart",
        "Hypoplastic right heart",
        "Ebsteins anomaly",
        "Idiopathic hypertrophic subaortic stenosis (IHSS)",
        "Interrupted aortic arch",
        "Mitral regurgitation",
        "Mitral stenosis",
        "Pulmonary atresia",
        "Pulmonary artery hypoplasia",
        "Patent ductus arteriosus",
        "Patent ductus arteriosus + OL",
        "Pulmonary valve stenosis",
        "Pulmonary valve stenosis + OL",
        "Subaortic stenosing ring",
        "Taussig-Bing",
        "Tricuspid atresia",
        "Transposition of great vessels",
        "Tetralogy of Fallot",
        "Univentricular heart",
        "Truncus arteriosus",
        "Ventricular septal defect",
        "Ventricular septal defect + OL",
        "Hole in Heart",
        "Missing Chamber",
        "Cardiac Deformity"
      ]
    },
    {
      "title": "ngs2",
      "conditions": [
        "Acute Myeloid Leukemia (AML)",
        "Bladder cancer (good For Dead Cust)",
        "Brain cancer",
        "Breast cancer",
        "Central Nervous System cancer (CNS)",
        "Cervical cancer",
        "Esophageal cancer",
        "Hodgkins Lymphoma",
        "Kidney cancer (good For Dead Cust)",
        "Leukemia (good For Dead Cust)",
        "Liver cancer (good For Dead Cust)",
        "Lung cancer",
        "Multiple myeloma",
        "Non-Hodgkins Lymphoma (nhl) (good For Dead Cust)",
        "Ovarian cancer",
        "Prostate cancer",
        "Rectal cancer",
        "Colon / Colorectal cancer",
        "Thyroid cancer",
        "ALS",
        "Aplastic anemia",
        "Cardiac birth defect",
        "Epilepsy",
        "Female infertility",
        "Immune disorders",
        "Kidney damage",
        "Miscarriage",
        "Multiple Sclerosis",
        "Myelodysplastic syndromes",
        "Parkinsons disease (good For Dead Cust)",
        "Renal toxicity/ disease",
        "Scleroderma"
      ]
    }
  ]
}
